japanese_asmr/__init__.py
japanese_asmr/command_line.py
japanese_asmr/parser.py
japanese_asmr-0.4.2.dist-info/METADATA
japanese_asmr-0.4.2.dist-info/WHEEL
japanese_asmr-0.4.2.dist-info/entry_points.txt
japanese_asmr-0.4.2.dist-info/top_level.txt
japanese_asmr-0.4.2.dist-info/RECORD
