Metadata-Version: 2.1
Name: japanese-asmr
Version: 0.4.2
Summary: A parser for ASMR recordings from https://japaneseasmr.com/
Home-page: https://github.com/marnixah/japanese-asmr-parser
Author: Marnixah
Author-email: japanese_asmr@marnixah.com
License: UNKNOWN
Project-URL: Bug Tracker, https://github.com/marnixah/japanese-asmr-parser/issues
Platform: UNKNOWN
Classifier: Programming Language :: Python :: 3
Classifier: License :: OSI Approved :: MIT License
Classifier: Operating System :: OS Independent
Requires-Python: >=3.6
Requires-Dist: requests-html
Requires-Dist: click
